<?xml version="1.0" encoding="UTF-8"?>
<hopsanobjectappearance version="0.3">
    <modelobject typename="MechanicAngularVelocitySensor" displayname="Angular Velocity Transducer">
        <icons>
            <icon scale="1" path="angularvelocitysensor_user.svg" iconrotation="ON" type="user"/>
            <icon scale="1" path="angularvelocitysensor_iso.svg" iconrotation="ON" type="iso"/>
        </icons>
        <ports>
            <port x="0.5" y="1" a="90" name="P1"/>
            <port x="0.5" y="0" a="270" name="out"/>
        </ports>
    </modelobject>
</hopsanobjectappearance>
