<?xml version='1.0' encoding='UTF-8'?>
<hopsanobjectappearance version="0.3">
    <modelobject sourcecode="MechanicVehicle1D.hpp" typename="MechanicVehicle1D" displayname="1D Road Vehicle">
        <icons>
            <icon scale="1" path="MechanicVehicle1D.svg" iconrotation="ON" type="user"/>
            <icon scale="1" path="MechanicVehicle1D.svg" iconrotation="ON" type="iso"/>
        </icons>
        <ports>
            <port x="1" y="0.8" a="0" name="fr"/>
            <port x="1" y="0.6" a="0" name="xc"/>
            <port x="1" y="0.5" a="0" name="vc"/>
            <port x="1" y="0.7" a="0" name="fd"/>
            <port x="0.2" y="1" a="90" name="Pmr1"/>
            <port x="0.8" y="1" a="90" name="Pmr2"/>
        </ports>
    </modelobject>
</hopsanobjectappearance>
